LICENSE.rst
MANIFEST.in
README.rst
setup.py
pwhash/__init__.py
pwhash/_commoncrypto.py
pwhash/_openssl.py
pwhash/algorithms.py
pwhash/config.py
pwhash/hashers.py
pwhash/packaging.py
pwhash/utils.py
pwhash.egg-info/PKG-INFO
pwhash.egg-info/SOURCES.txt
pwhash.egg-info/dependency_links.txt
pwhash.egg-info/entry_points.txt
pwhash.egg-info/not-zip-safe
pwhash.egg-info/requires.txt
pwhash.egg-info/top_level.txt
pwhash/__pycache__/_cffi__x8617cc2ex89609deb.c
pwhash/__pycache__/_cffi__xc1722c91x6005c88e.c
pwhash/__pycache__/_cffi__xdb6e3c2fx5d90566e.c
pwhash/tests/__init__.py
pwhash/tests/pwhashc.json
pwhash/tests/test_algorithms.py
pwhash/tests/test_commoncrypto.py
pwhash/tests/test_config.py
pwhash/tests/test_hashers.py
pwhash/tests/test_openssl.py
pwhash/tests/test_packaging.py
pwhash/tests/test_utils.py
pwhash/tests/utils.py
pwhash/tests/package/MANIFEST.in
pwhash/tests/package/setup.py
pwhash/tests/package/package/pwhash.json