Metadata-Version: 1.1
Name: pwhash
Version: 0.1.0
Summary: simple safe password hashing
Home-page: https://github.com/DasIch/pwhash
Author: Daniel Neuhäuser
Author-email: dasdasich@gmail.com
License: BSD
Platform: UNKNOWN
Classifier: Development Status :: 2 - Pre-Alpha
Classifier: License :: OSI Approved :: BSD License
Classifier: Programming Language :: Python :: 2.7
Classifier: Programming Language :: Python :: 3.3
Classifier: Programming Language :: Python :: Implementation :: CPython
Classifier: Programming Language :: Python :: Implementation :: PyPy
